douyin_summary_mcp/__init__.py
douyin_summary_mcp/aliyun_asr.py
douyin_summary_mcp/douyin_parser.py
douyin_summary_mcp/mcp_protocol_server.py
douyin_summary_mcp/mcp_server.py
douyin_summary_mcp/qwen_client.py
douyin_summary_mcp/rapidapi_client.py
douyin_summary_mcp-1.0.1.dist-info/licenses/LICENSE
douyin_summary_mcp-1.0.1.dist-info/METADATA
douyin_summary_mcp-1.0.1.dist-info/WHEEL
douyin_summary_mcp-1.0.1.dist-info/entry_points.txt
douyin_summary_mcp-1.0.1.dist-info/top_level.txt
douyin_summary_mcp-1.0.1.dist-info/RECORD
