Metadata-Version: 2.4
Name: douyin-summary-mcp
Version: 1.0.1
Summary: MCP服务：从抖音分享链接提取音频、进行语音识别并整理对话内容
Home-page: https://github.com/yourusername/douyin-summary-mcp
Author: Your Name
Author-email: Your Name <your.email@example.com>
License: MIT
Project-URL: Homepage, https://github.com/yourusername/douyin-summary-mcp
Project-URL: Documentation, https://github.com/yourusername/douyin-summary-mcp#readme
Project-URL: Repository, https://github.com/yourusername/douyin-summary-mcp
Project-URL: Issues, https://github.com/yourusername/douyin-summary-mcp/issues
Keywords: mcp,douyin,speech-recognition,asr,ai
Classifier: Development Status :: 4 - Beta
Classifier: Intended Audience :: Developers
Classifier: License :: OSI Approved :: MIT License
Classifier: Programming Language :: Python :: 3
Classifier: Programming Language :: Python :: 3.8
Classifier: Programming Language :: Python :: 3.9
Classifier: Programming Language :: Python :: 3.10
Classifier: Programming Language :: Python :: 3.11
Classifier: Programming Language :: Python :: 3.12
Classifier: Topic :: Software Development :: Libraries :: Python Modules
Classifier: Topic :: Multimedia :: Sound/Audio :: Speech
Requires-Python: >=3.8
License-File: LICENSE
Requires-Dist: requests>=2.31.0
Requires-Dist: dashscope>=1.17.0
Requires-Dist: python-dotenv>=1.0.0
Dynamic: author
Dynamic: home-page
Dynamic: license-file
Dynamic: requires-python
